django_odoo_orm/__init__.py
django_odoo_orm/apps.py
django_odoo_orm/context_processors.py
django_odoo_orm/settings.py
django_odoo_orm/views.py
django_odoo_orm-3.0.2.dist-info/LICENSE
django_odoo_orm-3.0.2.dist-info/METADATA
django_odoo_orm-3.0.2.dist-info/WHEEL
django_odoo_orm-3.0.2.dist-info/RECORD
