Metadata-Version: 2.1
Name: django-odoo-orm
Version: 3.0.2
Summary: A kind of Python ORM for Odoo XML-RPC API inspired by Django ORM.
Home-page: https://github.com/mistiru/django-odoo-orm
License: MIT
Author: mistiru
Author-email: dev@mistiru.me
Requires-Python: >=3.9,<4.0
Classifier: Framework :: Django
Classifier: Framework :: Django :: 3.2
Classifier: Framework :: Django :: 4.0
Classifier: Framework :: Django :: 4.1
Classifier: Framework :: Django :: 4.2
Classifier: Framework :: Django :: 5.0
Classifier: License :: OSI Approved :: MIT License
Classifier: Programming Language :: Python :: 3
Classifier: Programming Language :: Python :: 3.9
Classifier: Programming Language :: Python :: 3.10
Classifier: Programming Language :: Python :: 3.11
Classifier: Programming Language :: Python :: 3.12
Requires-Dist: Django (>=3.2,<6)
Requires-Dist: odoo-orm (>=2.0.0,<3.0.0)
